tests/__init__.py
tests/test_auto_window.py
tests/test_edit_message.py
tests/test_send_inline_keyboard.py
tests/test_send_message.py
tests/test_send_photo.py
tests/test_user_middleware.py
tests/test_window_creation.py
tgwindow/__init__.py
tgwindow/buttons.py
tgwindow/middleware.py
tgwindow/registration.py
tgwindow/sender.py
tgwindow/static_window.py
tgwindow/window_base.py
tgwindow/wrapper.py
tgwindow-2.0.2.dist-info/METADATA
tgwindow-2.0.2.dist-info/WHEEL
tgwindow-2.0.2.dist-info/top_level.txt
tgwindow-2.0.2.dist-info/RECORD
