Metadata-Version: 2.2
Name: tgwindow
Version: 2.0.2
Summary: Библиотека для создания простых окон в Telegram-боте с использованием aiogram 3.+
Home-page: https://github.com/belyankiss/tgwindow.git
Author: PyExecutor
Author-email: belyankiss@gmail.com
License: MIT
Project-URL: Bug Tracker, https://github.com/belyankiss/tgwindow/issues
Project-URL: Documentation, https://github.com/belyankiss/tgwindow#readme
Project-URL: Source Code, https://github.com/belyankiss/tgwindow
Keywords: telegram,aiogram,bot,windows,library
Classifier: Development Status :: 5 - Production/Stable
Classifier: Programming Language :: Python :: 3
Classifier: Programming Language :: Python :: 3.8
Classifier: Programming Language :: Python :: 3.9
Classifier: Programming Language :: Python :: 3.10
Classifier: License :: OSI Approved :: MIT License
Classifier: Operating System :: OS Independent
Classifier: Intended Audience :: Developers
Classifier: Topic :: Software Development :: Libraries
Requires-Python: >=3.8
Requires-Dist: aiogram>=3.0.0
Provides-Extra: dev
Requires-Dist: pytest; extra == "dev"
Requires-Dist: flake8; extra == "dev"
Requires-Dist: black; extra == "dev"
Dynamic: author
Dynamic: author-email
Dynamic: classifier
Dynamic: description
Dynamic: description-content-type
Dynamic: home-page
Dynamic: keywords
Dynamic: license
Dynamic: project-url
Dynamic: provides-extra
Dynamic: requires-dist
Dynamic: requires-python
Dynamic: summary
